<?xml version="1.0"?>
<ArrayOfSetup xmlns:xsi="http://www.w3.org/2001/XMLSchema-instance" xmlns:xsd="http://www.w3.org/2001/XMLSchema">
  <Setup>
    <results>
      <float>1.362069</float>
      <float>3.06920576</float>
      <float>1.04179907</float>
    </results>
    <betsCount>
      <int>22</int>
      <int>23</int>
      <int>32</int>
    </betsCount>
    <daysForFormPeriod>60</daysForFormPeriod>
    <monthForLevelPeriod>12</monthForLevelPeriod>
    <monthForH2H>36</monthForH2H>
    <mergeStatistic>false</mergeStatistic>
    <includeHomeH2H>false</includeHomeH2H>
    <matchCountForDefaultValue>0</matchCountForDefaultValue>
    <minValue>0.049999997</minValue>
    <maxValue>0.12999998</maxValue>
    <minKf>2</minKf>
    <maxKf>4</maxKf>
    <lampda>0.15</lampda>
    <kf>1</kf>
    <finishResult>4.35521</finishResult>
  </Setup>
  <Setup>
    <results>
      <float>1.43105507</float>
      <float>3.06029725</float>
      <float>0.9207261</float>
    </results>
    <betsCount>
      <int>31</int>
      <int>33</int>
      <int>49</int>
    </betsCount>
    <daysForFormPeriod>60</daysForFormPeriod>
    <monthForLevelPeriod>12</monthForLevelPeriod>
    <monthForH2H>36</monthForH2H>
    <mergeStatistic>false</mergeStatistic>
    <includeHomeH2H>false</includeHomeH2H>
    <matchCountForDefaultValue>0</matchCountForDefaultValue>
    <minValue>0.01</minValue>
    <maxValue>0.12999998</maxValue>
    <minKf>2</minKf>
    <maxKf>4</maxKf>
    <lampda>0.15</lampda>
    <kf>1</kf>
    <finishResult>4.03227758</finishResult>
  </Setup>
  <Setup>
    <results>
      <float>1.33561611</float>
      <float>2.82278228</float>
      <float>0.9794584</float>
    </results>
    <betsCount>
      <int>27</int>
      <int>28</int>
      <int>40</int>
    </betsCount>
    <daysForFormPeriod>60</daysForFormPeriod>
    <monthForLevelPeriod>12</monthForLevelPeriod>
    <monthForH2H>36</monthForH2H>
    <mergeStatistic>false</mergeStatistic>
    <includeHomeH2H>false</includeHomeH2H>
    <matchCountForDefaultValue>0</matchCountForDefaultValue>
    <minValue>0.03</minValue>
    <maxValue>0.12999998</maxValue>
    <minKf>2</minKf>
    <maxKf>4</maxKf>
    <lampda>0.15</lampda>
    <kf>1</kf>
    <finishResult>3.69270849</finishResult>
  </Setup>
  <Setup>
    <results>
      <float>1.4014343</float>
      <float>1.50149751</float>
      <float>1.50988543</float>
    </results>
    <betsCount>
      <int>24</int>
      <int>28</int>
      <int>28</int>
    </betsCount>
    <daysForFormPeriod>45</daysForFormPeriod>
    <monthForLevelPeriod>24</monthForLevelPeriod>
    <monthForH2H>36</monthForH2H>
    <mergeStatistic>false</mergeStatistic>
    <includeHomeH2H>false</includeHomeH2H>
    <matchCountForDefaultValue>0</matchCountForDefaultValue>
    <minValue>0.01</minValue>
    <maxValue>0.06999999</maxValue>
    <minKf>1</minKf>
    <maxKf>5</maxKf>
    <lampda>0.15</lampda>
    <kf>1</kf>
    <finishResult>3.17717671</finishResult>
  </Setup>
  <Setup>
    <results>
      <float>1.18263936</float>
      <float>2.86126924</float>
      <float>0.933616936</float>
    </results>
    <betsCount>
      <int>23</int>
      <int>26</int>
      <int>39</int>
    </betsCount>
    <daysForFormPeriod>60</daysForFormPeriod>
    <monthForLevelPeriod>12</monthForLevelPeriod>
    <monthForH2H>36</monthForH2H>
    <mergeStatistic>false</mergeStatistic>
    <includeHomeH2H>false</includeHomeH2H>
    <matchCountForDefaultValue>0</matchCountForDefaultValue>
    <minValue>0.049999997</minValue>
    <maxValue>0.149999976</maxValue>
    <minKf>2</minKf>
    <maxKf>4</maxKf>
    <lampda>0.15</lampda>
    <kf>1</kf>
    <finishResult>3.15921926</finishResult>
  </Setup>
  <Setup>
    <results>
      <float>0.9726083</float>
      <float>1.8510499</float>
      <float>1.7177422</float>
    </results>
    <betsCount>
      <int>26</int>
      <int>23</int>
      <int>29</int>
    </betsCount>
    <daysForFormPeriod>30</daysForFormPeriod>
    <monthForLevelPeriod>12</monthForLevelPeriod>
    <monthForH2H>24</monthForH2H>
    <mergeStatistic>false</mergeStatistic>
    <includeHomeH2H>false</includeHomeH2H>
    <matchCountForDefaultValue>0</matchCountForDefaultValue>
    <minValue>0.03</minValue>
    <maxValue>0.109999985</maxValue>
    <minKf>2</minKf>
    <maxKf>4</maxKf>
    <lampda>0.15</lampda>
    <kf>1</kf>
    <finishResult>3.0925312</finishResult>
  </Setup>
  <Setup>
    <results>
      <float>0.9430032</float>
      <float>1.73842168</float>
      <float>1.78305387</float>
    </results>
    <betsCount>
      <int>30</int>
      <int>29</int>
      <int>33</int>
    </betsCount>
    <daysForFormPeriod>30</daysForFormPeriod>
    <monthForLevelPeriod>12</monthForLevelPeriod>
    <monthForH2H>24</monthForH2H>
    <mergeStatistic>false</mergeStatistic>
    <includeHomeH2H>false</includeHomeH2H>
    <matchCountForDefaultValue>0</matchCountForDefaultValue>
    <minValue>0.01</minValue>
    <maxValue>0.109999985</maxValue>
    <minKf>2</minKf>
    <maxKf>4</maxKf>
    <lampda>0.15</lampda>
    <kf>1</kf>
    <finishResult>2.92302656</finishResult>
  </Setup>
  <Setup>
    <results>
      <float>1.35348523</float>
      <float>1.50149751</float>
      <float>1.30734265</float>
    </results>
    <betsCount>
      <int>22</int>
      <int>28</int>
      <int>23</int>
    </betsCount>
    <daysForFormPeriod>45</daysForFormPeriod>
    <monthForLevelPeriod>24</monthForLevelPeriod>
    <monthForH2H>36</monthForH2H>
    <mergeStatistic>false</mergeStatistic>
    <includeHomeH2H>false</includeHomeH2H>
    <matchCountForDefaultValue>0</matchCountForDefaultValue>
    <minValue>0.01</minValue>
    <maxValue>0.06999999</maxValue>
    <minKf>1</minKf>
    <maxKf>4</maxKf>
    <lampda>0.15</lampda>
    <kf>1</kf>
    <finishResult>2.6568532</finishResult>
  </Setup>
  <Setup>
    <results>
      <float>0.989612937</float>
      <float>1.6919558</float>
      <float>1.48292017</float>
    </results>
    <betsCount>
      <int>27</int>
      <int>28</int>
      <int>26</int>
    </betsCount>
    <daysForFormPeriod>30</daysForFormPeriod>
    <monthForLevelPeriod>12</monthForLevelPeriod>
    <monthForH2H>24</monthForH2H>
    <mergeStatistic>false</mergeStatistic>
    <includeHomeH2H>false</includeHomeH2H>
    <matchCountForDefaultValue>0</matchCountForDefaultValue>
    <minValue>0.03</minValue>
    <maxValue>0.12999998</maxValue>
    <minKf>2</minKf>
    <maxKf>4</maxKf>
    <lampda>0.14</lampda>
    <kf>1</kf>
    <finishResult>2.48297381</finishResult>
  </Setup>
  <Setup>
    <results>
      <float>0.936677754</float>
      <float>1.43533158</float>
      <float>1.64155483</float>
    </results>
    <betsCount>
      <int>30</int>
      <int>30</int>
      <int>31</int>
    </betsCount>
    <daysForFormPeriod>30</daysForFormPeriod>
    <monthForLevelPeriod>12</monthForLevelPeriod>
    <monthForH2H>24</monthForH2H>
    <mergeStatistic>false</mergeStatistic>
    <includeHomeH2H>false</includeHomeH2H>
    <matchCountForDefaultValue>0</matchCountForDefaultValue>
    <minValue>0.01</minValue>
    <maxValue>0.12999998</maxValue>
    <minKf>2</minKf>
    <maxKf>4</maxKf>
    <lampda>0.14</lampda>
    <kf>1</kf>
    <finishResult>2.20697713</finishResult>
  </Setup>
  <Setup>
    <results>
      <float>1.14893746</float>
      <float>1.5350771</float>
      <float>1.24206507</float>
    </results>
    <betsCount>
      <int>22</int>
      <int>25</int>
      <int>23</int>
    </betsCount>
    <daysForFormPeriod>30</daysForFormPeriod>
    <monthForLevelPeriod>12</monthForLevelPeriod>
    <monthForH2H>24</monthForH2H>
    <mergeStatistic>false</mergeStatistic>
    <includeHomeH2H>false</includeHomeH2H>
    <matchCountForDefaultValue>0</matchCountForDefaultValue>
    <minValue>0.01</minValue>
    <maxValue>0.06999999</maxValue>
    <minKf>1</minKf>
    <maxKf>5</maxKf>
    <lampda>0.14</lampda>
    <kf>1</kf>
    <finishResult>2.19063973</finishResult>
  </Setup>
  <Setup>
    <results>
      <float>0.9014252</float>
      <float>1.310079</float>
      <float>1.32827473</float>
    </results>
    <betsCount>
      <int>23</int>
      <int>24</int>
      <int>25</int>
    </betsCount>
    <daysForFormPeriod>30</daysForFormPeriod>
    <monthForLevelPeriod>12</monthForLevelPeriod>
    <monthForH2H>24</monthForH2H>
    <mergeStatistic>false</mergeStatistic>
    <includeHomeH2H>false</includeHomeH2H>
    <matchCountForDefaultValue>0</matchCountForDefaultValue>
    <minValue>0.01</minValue>
    <maxValue>0.08999999</maxValue>
    <minKf>2</minKf>
    <maxKf>4</maxKf>
    <lampda>0.14</lampda>
    <kf>1</kf>
    <finishResult>1.56861031</finishResult>
  </Setup>
  <Setup>
    <results>
      <float>0.9054972</float>
      <float>1.02766788</float>
      <float>1.47026026</float>
    </results>
    <betsCount>
      <int>22</int>
      <int>21</int>
      <int>29</int>
    </betsCount>
    <daysForFormPeriod>30</daysForFormPeriod>
    <monthForLevelPeriod>24</monthForLevelPeriod>
    <monthForH2H>36</monthForH2H>
    <mergeStatistic>false</mergeStatistic>
    <includeHomeH2H>false</includeHomeH2H>
    <matchCountForDefaultValue>0</matchCountForDefaultValue>
    <minValue>0.01</minValue>
    <maxValue>0.06999999</maxValue>
    <minKf>1</minKf>
    <maxKf>5</maxKf>
    <lampda>0.14</lampda>
    <kf>1</kf>
    <finishResult>1.36815131</finishResult>
  </Setup>
  <Setup>
    <results>
      <float>0.921371937</float>
      <float>1.51409125</float>
      <float>0.9573256</float>
    </results>
    <betsCount>
      <int>23</int>
      <int>27</int>
      <int>35</int>
    </betsCount>
    <daysForFormPeriod>45</daysForFormPeriod>
    <monthForLevelPeriod>24</monthForLevelPeriod>
    <monthForH2H>24</monthForH2H>
    <mergeStatistic>false</mergeStatistic>
    <includeHomeH2H>false</includeHomeH2H>
    <matchCountForDefaultValue>0</matchCountForDefaultValue>
    <minValue>0.01</minValue>
    <maxValue>0.08999999</maxValue>
    <minKf>1</minKf>
    <maxKf>4</maxKf>
    <lampda>0.14</lampda>
    <kf>1</kf>
    <finishResult>1.3355087</finishResult>
  </Setup>
  <Setup>
    <results>
      <float>1.29754066</float>
      <float>0.9313942</float>
      <float>1.04038012</float>
    </results>
    <betsCount>
      <int>23</int>
      <int>24</int>
      <int>39</int>
    </betsCount>
    <daysForFormPeriod>30</daysForFormPeriod>
    <monthForLevelPeriod>24</monthForLevelPeriod>
    <monthForH2H>24</monthForH2H>
    <mergeStatistic>false</mergeStatistic>
    <includeHomeH2H>false</includeHomeH2H>
    <matchCountForDefaultValue>0</matchCountForDefaultValue>
    <minValue>0.01</minValue>
    <maxValue>0.08999999</maxValue>
    <minKf>1</minKf>
    <maxKf>5</maxKf>
    <lampda>0.14</lampda>
    <kf>1</kf>
    <finishResult>1.25732207</finishResult>
  </Setup>
  <Setup>
    <results>
      <float>0.9834922</float>
      <float>1.14253211</float>
      <float>1.03444541</float>
    </results>
    <betsCount>
      <int>21</int>
      <int>22</int>
      <int>36</int>
    </betsCount>
    <daysForFormPeriod>30</daysForFormPeriod>
    <monthForLevelPeriod>24</monthForLevelPeriod>
    <monthForH2H>24</monthForH2H>
    <mergeStatistic>false</mergeStatistic>
    <includeHomeH2H>false</includeHomeH2H>
    <matchCountForDefaultValue>0</matchCountForDefaultValue>
    <minValue>0.01</minValue>
    <maxValue>0.08999999</maxValue>
    <minKf>1</minKf>
    <maxKf>4</maxKf>
    <lampda>0.14</lampda>
    <kf>1</kf>
    <finishResult>1.16237676</finishResult>
  </Setup>
  <Setup>
    <results>
      <float>1.29754066</float>
      <float>0.9313942</float>
      <float>0.933095932</float>
    </results>
    <betsCount>
      <int>23</int>
      <int>24</int>
      <int>36</int>
    </betsCount>
    <daysForFormPeriod>30</daysForFormPeriod>
    <monthForLevelPeriod>24</monthForLevelPeriod>
    <monthForH2H>24</monthForH2H>
    <mergeStatistic>false</mergeStatistic>
    <includeHomeH2H>false</includeHomeH2H>
    <matchCountForDefaultValue>0</matchCountForDefaultValue>
    <minValue>0.01</minValue>
    <maxValue>0.08999999</maxValue>
    <minKf>2</minKf>
    <maxKf>5</maxKf>
    <lampda>0.14</lampda>
    <kf>1</kf>
    <finishResult>1.12766683</finishResult>
  </Setup>
  <Setup>
    <results>
      <float>0.9136144</float>
      <float>1.28003168</float>
      <float>0.962065935</float>
    </results>
    <betsCount>
      <int>23</int>
      <int>23</int>
      <int>24</int>
    </betsCount>
    <daysForFormPeriod>30</daysForFormPeriod>
    <monthForLevelPeriod>12</monthForLevelPeriod>
    <monthForH2H>24</monthForH2H>
    <mergeStatistic>false</mergeStatistic>
    <includeHomeH2H>false</includeHomeH2H>
    <matchCountForDefaultValue>0</matchCountForDefaultValue>
    <minValue>0.01</minValue>
    <maxValue>0.06999999</maxValue>
    <minKf>2</minKf>
    <maxKf>5</maxKf>
    <lampda>0.15</lampda>
    <kf>1</kf>
    <finishResult>1.12509322</finishResult>
  </Setup>
  <Setup>
    <results>
      <float>0.992122531</float>
      <float>1.01239944</float>
      <float>1.05871654</float>
    </results>
    <betsCount>
      <int>24</int>
      <int>29</int>
      <int>30</int>
    </betsCount>
    <daysForFormPeriod>30</daysForFormPeriod>
    <monthForLevelPeriod>12</monthForLevelPeriod>
    <monthForH2H>24</monthForH2H>
    <mergeStatistic>false</mergeStatistic>
    <includeHomeH2H>false</includeHomeH2H>
    <matchCountForDefaultValue>0</matchCountForDefaultValue>
    <minValue>0.01</minValue>
    <maxValue>0.12999998</maxValue>
    <minKf>2</minKf>
    <maxKf>4</maxKf>
    <lampda>0.13</lampda>
    <kf>1</kf>
    <finishResult>1.06340063</finishResult>
  </Setup>
  <Setup>
    <results>
      <float>0.9834922</float>
      <float>1.14253211</float>
      <float>0.927773058</float>
    </results>
    <betsCount>
      <int>21</int>
      <int>22</int>
      <int>33</int>
    </betsCount>
    <daysForFormPeriod>30</daysForFormPeriod>
    <monthForLevelPeriod>24</monthForLevelPeriod>
    <monthForH2H>24</monthForH2H>
    <mergeStatistic>false</mergeStatistic>
    <includeHomeH2H>false</includeHomeH2H>
    <matchCountForDefaultValue>0</matchCountForDefaultValue>
    <minValue>0.01</minValue>
    <maxValue>0.08999999</maxValue>
    <minKf>2</minKf>
    <maxKf>4</maxKf>
    <lampda>0.14</lampda>
    <kf>1</kf>
    <finishResult>1.042512</finishResult>
  </Setup>
  <Setup>
    <results>
      <float>0.989734352</float>
      <float>1.028641</float>
      <float>0.917945</float>
    </results>
    <betsCount>
      <int>26</int>
      <int>27</int>
      <int>33</int>
    </betsCount>
    <daysForFormPeriod>30</daysForFormPeriod>
    <monthForLevelPeriod>12</monthForLevelPeriod>
    <monthForH2H>24</monthForH2H>
    <mergeStatistic>false</mergeStatistic>
    <includeHomeH2H>false</includeHomeH2H>
    <matchCountForDefaultValue>0</matchCountForDefaultValue>
    <minValue>0.01</minValue>
    <maxValue>0.149999976</maxValue>
    <minKf>3</minKf>
    <maxKf>4</maxKf>
    <lampda>0.15</lampda>
    <kf>1</kf>
    <finishResult>0.934542656</finishResult>
  </Setup>
</ArrayOfSetup>